py_checksum/checksum.py
py_checksum/cli.py
py_checksum-0.5.1.dist-info/LICENSE
py_checksum-0.5.1.dist-info/METADATA
py_checksum-0.5.1.dist-info/WHEEL
py_checksum-0.5.1.dist-info/entry_points.txt
py_checksum-0.5.1.dist-info/RECORD
